AUTHORS
ChangeLog
MANIFEST.in
README.rst
requirements.txt
setup.cfg
setup.py
leonardo_bootstrap_admin/__init__.py
leonardo_bootstrap_admin/settings.py
leonardo_bootstrap_admin.egg-info/PKG-INFO
leonardo_bootstrap_admin.egg-info/SOURCES.txt
leonardo_bootstrap_admin.egg-info/dependency_links.txt
leonardo_bootstrap_admin.egg-info/not-zip-safe
leonardo_bootstrap_admin.egg-info/pbr.json
leonardo_bootstrap_admin.egg-info/requires.txt
leonardo_bootstrap_admin.egg-info/top_level.txt
leonardo_bootstrap_admin/templates/admin/base.html
leonardo_bootstrap_admin/templates/admin/base_site.html
leonardo_bootstrap_admin/templates/admin/dashboard.html
leonardo_bootstrap_admin/templates/admin/login.html